Metadata-Version: 2.1
Name: celebrities-learning-test
Version: 0.0.1
Summary: Mock package that allows you to find a celebrty by date of birth
Home-page: https://github.com/IvanYingX/project_structure-pypi.git
Author: Ivan Ying
License: MIT
Platform: UNKNOWN
License-File: LICENSE
